[
    {
        "key": "group_64bb8ae7d3132",
        "title": "icl price",
        "fields": [
            {
                "key": "field_64bb8ae7d9980",
                "label": "CONSULTATION",
                "name": "section_1",
                "aria-label": "",
                "type": "group",
                "instructions": "",
                "required": 0,
                "conditional_logic": 0,
                "wrapper": {
                    "width": "",
                    "class": "",
                    "id": ""
                },
                "layout": "block",
                "sub_fields": [
                    {
                        "key": "field_64bb8ae861777",
                        "label": "Sub Heading",
                        "name": "sub_heading",
                        "aria-label": "",
                        "type": "text",
                        "instructions": "",
                        "required": 0,
                        "conditional_logic": 0,
                        "wrapper": {
                            "width": "",
                            "class": "",
                            "id": ""
                        },
                        "default_value": "",
                        "maxlength": "",
                        "placeholder": "",
                        "prepend": "",
                        "append": ""
                    },
                    {
                        "key": "field_64bb8ae8617b9",
                        "label": "Heading",
                        "name": "heading",
                        "aria-label": "",
                        "type": "group",
                        "instructions": "",
                        "required": 0,
                        "conditional_logic": 0,
                        "wrapper": {
                            "width": "",
                            "class": "",
                            "id": ""
                        },
                        "layout": "block",
                        "sub_fields": [
                            {
                                "key": "field_64bb8ae96e291",
                                "label": "Light Heading",
                                "name": "light_heading",
                                "aria-label": "",
                                "type": "text",
                                "instructions": "",
                                "required": 0,
                                "conditional_logic": 0,
                                "wrapper": {
                                    "width": "",
                                    "class": "",
                                    "id": ""
                                },
                                "default_value": "",
                                "maxlength": "",
                                "placeholder": "",
                                "prepend": "",
                                "append": ""
                            },
                            {
                                "key": "field_64bb8ae96e2d5",
                                "label": "Bold Heading",
                                "name": "bold_heading",
                                "aria-label": "",
                                "type": "text",
                                "instructions": "",
                                "required": 0,
                                "conditional_logic": 0,
                                "wrapper": {
                                    "width": "",
                                    "class": "",
                                    "id": ""
                                },
                                "default_value": "",
                                "maxlength": "",
                                "placeholder": "",
                                "prepend": "",
                                "append": ""
                            }
                        ]
                    },
                    {
                        "key": "field_64bb8ae8617f9",
                        "label": "lists",
                        "name": "lists",
                        "aria-label": "",
                        "type": "repeater",
                        "instructions": "",
                        "required": 0,
                        "conditional_logic": 0,
                        "wrapper": {
                            "width": "",
                            "class": "",
                            "id": ""
                        },
                        "layout": "table",
                        "pagination": 0,
                        "min": 0,
                        "max": 0,
                        "collapsed": "",
                        "button_label": "Add Row",
                        "rows_per_page": 20,
                        "sub_fields": [
                            {
                                "key": "field_64bb8aeb5f412",
                                "label": "list",
                                "name": "list",
                                "aria-label": "",
                                "type": "textarea",
                                "instructions": "",
                                "required": 0,
                                "conditional_logic": 0,
                                "wrapper": {
                                    "width": "",
                                    "class": "",
                                    "id": ""
                                },
                                "default_value": "",
                                "maxlength": "",
                                "rows": "",
                                "placeholder": "",
                                "new_lines": "",
                                "parent_repeater": "field_64bb8ae8617f9"
                            }
                        ]
                    },
                    {
                        "key": "field_64bb8ae86182e",
                        "label": "Image",
                        "name": "image",
                        "aria-label": "",
                        "type": "image",
                        "instructions": "",
                        "required": 0,
                        "conditional_logic": 0,
                        "wrapper": {
                            "width": "",
                            "class": "",
                            "id": ""
                        },
                        "return_format": "url",
                        "library": "all",
                        "min_width": "",
                        "min_height": "",
                        "min_size": "",
                        "max_width": "",
                        "max_height": "",
                        "max_size": "",
                        "mime_types": "",
                        "preview_size": "medium"
                    },
                    {
                        "key": "field_64bb8ae861871",
                        "label": "Large Image",
                        "name": "large_image",
                        "aria-label": "",
                        "type": "image",
                        "instructions": "",
                        "required": 0,
                        "conditional_logic": 0,
                        "wrapper": {
                            "width": "",
                            "class": "",
                            "id": ""
                        },
                        "return_format": "url",
                        "library": "all",
                        "min_width": "",
                        "min_height": "",
                        "min_size": "",
                        "max_width": "",
                        "max_height": "",
                        "max_size": "",
                        "mime_types": "",
                        "preview_size": "medium"
                    }
                ]
            },
            {
                "key": "field_64bb8ae7d99bc",
                "label": "ICL FINANCE",
                "name": "section_2",
                "aria-label": "",
                "type": "group",
                "instructions": "",
                "required": 0,
                "conditional_logic": 0,
                "wrapper": {
                    "width": "",
                    "class": "",
                    "id": ""
                },
                "layout": "block",
                "sub_fields": [
                    {
                        "key": "field_64bb8aee81f3a",
                        "label": "title",
                        "name": "title",
                        "aria-label": "",
                        "type": "text",
                        "instructions": "",
                        "required": 0,
                        "conditional_logic": 0,
                        "wrapper": {
                            "width": "",
                            "class": "",
                            "id": ""
                        },
                        "default_value": "",
                        "maxlength": "",
                        "placeholder": "",
                        "prepend": "",
                        "append": ""
                    },
                    {
                        "key": "field_64bb8aee81f7d",
                        "label": "heading",
                        "name": "heading",
                        "aria-label": "",
                        "type": "group",
                        "instructions": "",
                        "required": 0,
                        "conditional_logic": 0,
                        "wrapper": {
                            "width": "",
                            "class": "",
                            "id": ""
                        },
                        "layout": "block",
                        "sub_fields": [
                            {
                                "key": "field_64bb8aef4d1fc",
                                "label": "Light Heading",
                                "name": "light_heading",
                                "aria-label": "",
                                "type": "text",
                                "instructions": "",
                                "required": 0,
                                "conditional_logic": 0,
                                "wrapper": {
                                    "width": "",
                                    "class": "",
                                    "id": ""
                                },
                                "default_value": "",
                                "maxlength": "",
                                "placeholder": "",
                                "prepend": "",
                                "append": ""
                            },
                            {
                                "key": "field_64bb8aef4d239",
                                "label": "Bold Heading",
                                "name": "bold_heading",
                                "aria-label": "",
                                "type": "text",
                                "instructions": "",
                                "required": 0,
                                "conditional_logic": 0,
                                "wrapper": {
                                    "width": "",
                                    "class": "",
                                    "id": ""
                                },
                                "default_value": "",
                                "maxlength": "",
                                "placeholder": "",
                                "prepend": "",
                                "append": ""
                            }
                        ]
                    },
                    {
                        "key": "field_64bb8aee81fbe",
                        "label": "subheading",
                        "name": "subheading",
                        "aria-label": "",
                        "type": "text",
                        "instructions": "",
                        "required": 0,
                        "conditional_logic": 0,
                        "wrapper": {
                            "width": "",
                            "class": "",
                            "id": ""
                        },
                        "default_value": "",
                        "maxlength": "",
                        "placeholder": "",
                        "prepend": "",
                        "append": ""
                    },
                    {
                        "key": "field_64bb8aee82005",
                        "label": "descriptions",
                        "name": "descriptions",
                        "aria-label": "",
                        "type": "repeater",
                        "instructions": "",
                        "required": 0,
                        "conditional_logic": 0,
                        "wrapper": {
                            "width": "",
                            "class": "",
                            "id": ""
                        },
                        "layout": "table",
                        "pagination": 0,
                        "min": 0,
                        "max": 0,
                        "collapsed": "",
                        "button_label": "Add Row",
                        "rows_per_page": 20,
                        "sub_fields": [
                            {
                                "key": "field_64bb8af1b14fc",
                                "label": "description",
                                "name": "description",
                                "aria-label": "",
                                "type": "textarea",
                                "instructions": "",
                                "required": 0,
                                "conditional_logic": 0,
                                "wrapper": {
                                    "width": "",
                                    "class": "",
                                    "id": ""
                                },
                                "default_value": "",
                                "maxlength": "",
                                "rows": "",
                                "placeholder": "",
                                "new_lines": "",
                                "parent_repeater": "field_64bb8aee82005"
                            }
                        ]
                    },
                    {
                        "key": "field_64bb8aee82044",
                        "label": "Image",
                        "name": "image",
                        "aria-label": "",
                        "type": "image",
                        "instructions": "",
                        "required": 0,
                        "conditional_logic": 0,
                        "wrapper": {
                            "width": "",
                            "class": "",
                            "id": ""
                        },
                        "return_format": "url",
                        "library": "all",
                        "min_width": "",
                        "min_height": "",
                        "min_size": "",
                        "max_width": "",
                        "max_height": "",
                        "max_size": "",
                        "mime_types": "",
                        "preview_size": "medium"
                    },
                    {
                        "key": "field_64bb8aee82084",
                        "label": "Large Image",
                        "name": "large_image",
                        "aria-label": "",
                        "type": "image",
                        "instructions": "",
                        "required": 0,
                        "conditional_logic": 0,
                        "wrapper": {
                            "width": "",
                            "class": "",
                            "id": ""
                        },
                        "return_format": "url",
                        "library": "all",
                        "min_width": "",
                        "min_height": "",
                        "min_size": "",
                        "max_width": "",
                        "max_height": "",
                        "max_size": "",
                        "mime_types": "",
                        "preview_size": "medium"
                    },
                    {
                        "key": "field_64bb8aee8213f",
                        "label": "lists",
                        "name": "lists",
                        "aria-label": "",
                        "type": "repeater",
                        "instructions": "",
                        "required": 0,
                        "conditional_logic": 0,
                        "wrapper": {
                            "width": "",
                            "class": "",
                            "id": ""
                        },
                        "layout": "table",
                        "pagination": 0,
                        "min": 0,
                        "max": 0,
                        "collapsed": "",
                        "button_label": "Add Row",
                        "rows_per_page": 20,
                        "sub_fields": [
                            {
                                "key": "field_64bb8af51db81",
                                "label": "list",
                                "name": "list",
                                "aria-label": "",
                                "type": "textarea",
                                "instructions": "",
                                "required": 0,
                                "conditional_logic": 0,
                                "wrapper": {
                                    "width": "",
                                    "class": "",
                                    "id": ""
                                },
                                "default_value": "",
                                "maxlength": "",
                                "rows": "",
                                "placeholder": "",
                                "new_lines": "",
                                "parent_repeater": "field_64bb8aee8213f"
                            }
                        ]
                    }
                ]
            },
            {
                "key": "field_64bb8ae7d99f6",
                "label": "Price Section",
                "name": "lsk_price",
                "aria-label": "",
                "type": "repeater",
                "instructions": "",
                "required": 0,
                "conditional_logic": 0,
                "wrapper": {
                    "width": "",
                    "class": "",
                    "id": ""
                },
                "layout": "table",
                "pagination": 0,
                "min": 0,
                "max": 0,
                "collapsed": "",
                "button_label": "Add Row",
                "rows_per_page": 20,
                "sub_fields": [
                    {
                        "key": "field_64bb8af76f894",
                        "label": "price",
                        "name": "price",
                        "aria-label": "",
                        "type": "text",
                        "instructions": "",
                        "required": 0,
                        "conditional_logic": 0,
                        "wrapper": {
                            "width": "",
                            "class": "",
                            "id": ""
                        },
                        "default_value": "",
                        "maxlength": "",
                        "placeholder": "",
                        "prepend": "",
                        "append": "",
                        "parent_repeater": "field_64bb8ae7d99f6"
                    },
                    {
                        "key": "field_64bb8af76f8f5",
                        "label": "Price Text",
                        "name": "priceText",
                        "aria-label": "",
                        "type": "text",
                        "instructions": "",
                        "required": 0,
                        "conditional_logic": 0,
                        "wrapper": {
                            "width": "",
                            "class": "",
                            "id": ""
                        },
                        "default_value": "",
                        "maxlength": "",
                        "placeholder": "",
                        "prepend": "",
                        "append": "",
                        "parent_repeater": "field_64bb8ae7d99f6"
                    },
                    {
                        "key": "field_64bb8af76f93c",
                        "label": "Price Description",
                        "name": "priceDescription",
                        "aria-label": "",
                        "type": "text",
                        "instructions": "",
                        "required": 0,
                        "conditional_logic": 0,
                        "wrapper": {
                            "width": "",
                            "class": "",
                            "id": ""
                        },
                        "default_value": "",
                        "maxlength": "",
                        "placeholder": "",
                        "prepend": "",
                        "append": "",
                        "parent_repeater": "field_64bb8ae7d99f6"
                    }
                ]
            },
            {
                "key": "field_64bb8ae7d9a0d",
                "label": "Laser eye surgery",
                "name": "section_3",
                "aria-label": "",
                "type": "group",
                "instructions": "",
                "required": 0,
                "conditional_logic": 0,
                "wrapper": {
                    "width": "",
                    "class": "",
                    "id": ""
                },
                "layout": "block",
                "sub_fields": [
                    {
                        "key": "field_64bb8afa0b877",
                        "label": "title",
                        "name": "title",
                        "aria-label": "",
                        "type": "text",
                        "instructions": "",
                        "required": 0,
                        "conditional_logic": 0,
                        "wrapper": {
                            "width": "",
                            "class": "",
                            "id": ""
                        },
                        "default_value": "",
                        "maxlength": "",
                        "placeholder": "",
                        "prepend": "",
                        "append": ""
                    },
                    {
                        "key": "field_64bb8afa0b8c0",
                        "label": "description",
                        "name": "description",
                        "aria-label": "",
                        "type": "text",
                        "instructions": "",
                        "required": 0,
                        "conditional_logic": 0,
                        "wrapper": {
                            "width": "",
                            "class": "",
                            "id": ""
                        },
                        "default_value": "",
                        "maxlength": "",
                        "placeholder": "",
                        "prepend": "",
                        "append": ""
                    },
                    {
                        "key": "field_64bb8afa0b904",
                        "label": "Image",
                        "name": "image",
                        "aria-label": "",
                        "type": "image",
                        "instructions": "",
                        "required": 0,
                        "conditional_logic": 0,
                        "wrapper": {
                            "width": "",
                            "class": "",
                            "id": ""
                        },
                        "return_format": "url",
                        "library": "all",
                        "min_width": "",
                        "min_height": "",
                        "min_size": "",
                        "max_width": "",
                        "max_height": "",
                        "max_size": "",
                        "mime_types": "",
                        "preview_size": "medium"
                    },
                    {
                        "key": "field_64bb8afa0b92d",
                        "label": "large Image",
                        "name": "large_image",
                        "aria-label": "",
                        "type": "image",
                        "instructions": "",
                        "required": 0,
                        "conditional_logic": 0,
                        "wrapper": {
                            "width": "",
                            "class": "",
                            "id": ""
                        },
                        "return_format": "url",
                        "library": "all",
                        "min_width": "",
                        "min_height": "",
                        "min_size": "",
                        "max_width": "",
                        "max_height": "",
                        "max_size": "",
                        "mime_types": "",
                        "preview_size": "medium"
                    }
                ]
            },
            {
                "key": "field_64bb8ae7d9a4a",
                "label": "Speak To Our Friendly Team",
                "name": "speaktoteam",
                "aria-label": "",
                "type": "group",
                "instructions": "",
                "required": 0,
                "conditional_logic": 0,
                "wrapper": {
                    "width": "",
                    "class": "",
                    "id": ""
                },
                "layout": "block",
                "sub_fields": [
                    {
                        "key": "field_64bb8afd623cc",
                        "label": "subtitle",
                        "name": "subtitle",
                        "aria-label": "",
                        "type": "text",
                        "instructions": "",
                        "required": 0,
                        "conditional_logic": 0,
                        "wrapper": {
                            "width": "",
                            "class": "",
                            "id": ""
                        },
                        "default_value": "",
                        "maxlength": "",
                        "placeholder": "",
                        "prepend": "",
                        "append": ""
                    },
                    {
                        "key": "field_64bb8afd623e5",
                        "label": "title",
                        "name": "title",
                        "aria-label": "",
                        "type": "text",
                        "instructions": "",
                        "required": 0,
                        "conditional_logic": 0,
                        "wrapper": {
                            "width": "",
                            "class": "",
                            "id": ""
                        },
                        "default_value": "",
                        "maxlength": "",
                        "placeholder": "",
                        "prepend": "",
                        "append": ""
                    }
                ]
            },
            {
                "key": "field_64bb8ae7d9abe",
                "label": "Image Section",
                "name": "section_4",
                "aria-label": "",
                "type": "group",
                "instructions": "",
                "required": 0,
                "conditional_logic": 0,
                "wrapper": {
                    "width": "",
                    "class": "",
                    "id": ""
                },
                "layout": "block",
                "sub_fields": [
                    {
                        "key": "field_64bb8b01e22da",
                        "label": "title",
                        "name": "title",
                        "aria-label": "",
                        "type": "wysiwyg",
                        "instructions": "",
                        "required": 0,
                        "conditional_logic": 0,
                        "wrapper": {
                            "width": "",
                            "class": "",
                            "id": ""
                        },
                        "default_value": "",
                        "tabs": "all",
                        "toolbar": "full",
                        "media_upload": 1,
                        "delay": 0
                    },
                    {
                        "key": "field_64bb8b01e232d",
                        "label": "Image",
                        "name": "image",
                        "aria-label": "",
                        "type": "image",
                        "instructions": "",
                        "required": 0,
                        "conditional_logic": 0,
                        "wrapper": {
                            "width": "",
                            "class": "",
                            "id": ""
                        },
                        "return_format": "url",
                        "library": "all",
                        "min_width": "",
                        "min_height": "",
                        "min_size": "",
                        "max_width": "",
                        "max_height": "",
                        "max_size": "",
                        "mime_types": "",
                        "preview_size": "medium"
                    },
                    {
                        "key": "field_64bb8b01e2371",
                        "label": "large Image",
                        "name": "large_image",
                        "aria-label": "",
                        "type": "image",
                        "instructions": "",
                        "required": 0,
                        "conditional_logic": 0,
                        "wrapper": {
                            "width": "",
                            "class": "",
                            "id": ""
                        },
                        "return_format": "url",
                        "library": "all",
                        "min_width": "",
                        "min_height": "",
                        "min_size": "",
                        "max_width": "",
                        "max_height": "",
                        "max_size": "",
                        "mime_types": "",
                        "preview_size": "medium"
                    }
                ]
            }
        ],
        "location": [
            [
                {
                    "param": "page",
                    "operator": "==",
                    "value": "13294"
                }
            ]
        ],
        "menu_order": 0,
        "position": "normal",
        "style": "default",
        "label_placement": "top",
        "instruction_placement": "label",
        "hide_on_screen": "",
        "active": true,
        "description": "",
        "show_in_rest": 1
    }
]